cerberus_list_schema/__init__.py
cerberus_list_schema/tests/__init__.py
cerberus_list_schema/tests/test_multiuse.py
cerberus_list_schema/tests/test_normalization.py
cerberus_list_schema/tests/test_normalization_as_dict.py
cerberus_list_schema/tests/test_normalization_as_object.py
cerberus_list_schema/tests/test_validation.py
cerberus_list_schema/tests/test_data/__init__.py
cerberus_list_schema/tests/test_data/dict_schemas.py
cerberus_list_schema/tests/test_data/list_schemas.py
cerberus_list_schema/tests/test_data/multiuse_schema.py
cerberus_list_schema/tests/test_data/utils.py
cerberus_list_schema-1.0.3.dist-info/LICENSE
cerberus_list_schema-1.0.3.dist-info/METADATA
cerberus_list_schema-1.0.3.dist-info/WHEEL
cerberus_list_schema-1.0.3.dist-info/top_level.txt
cerberus_list_schema-1.0.3.dist-info/RECORD
