Metadata-Version: 2.1
Name: cerberus-list-schema
Version: 1.0.3
Summary: Cerburus based validation extended to support list schemas and list transposition to dictionary and python objects
Home-page: https://github.com/Firepubes/cerberus-list-schema
Author: Amy Summers
Author-email: amy@sakuradigital.co.uk
License: MIT
Keywords: validation,schema,dictionaries,normalization,list,array,cerberus,object
Platform: UNKNOWN
Classifier: Programming Language :: Python :: 3
Classifier: License :: OSI Approved :: MIT License
Classifier: Operating System :: OS Independent
Requires-Python: >=3.4
Requires-Dist: cerberus
Requires-Dist: munch
